cli/__init__.py
cli/cli.py
cli_app_yml-1.0.2.dist-info/entry_points.txt
cli_app_yml-1.0.2.dist-info/LICENSE
cli_app_yml-1.0.2.dist-info/WHEEL
cli_app_yml-1.0.2.dist-info/METADATA
cli_app_yml-1.0.2.dist-info/RECORD
