Metadata-Version: 2.1
Name: cli-app-yml
Version: 1.0.2
Summary: CLI application creater based out of argparse. entrypoints for different subcommands are defined using yml
Author: Varun Bhat
Author-email: varunbhat@apple.com
Requires-Python: >=3.8,<4.0
Classifier: Programming Language :: Python :: 3
Classifier: Programming Language :: Python :: 3.8
Classifier: Programming Language :: Python :: 3.9
Classifier: Programming Language :: Python :: 3.10
Classifier: Programming Language :: Python :: 3.11
Requires-Dist: python-dotenv (>=0.21.0,<0.22.0)
Requires-Dist: pyyaml (>=6.0,<7.0)
